avp/__init__.py
avp/__main__.py
avp/cli.py
avp/command.py
avp/component.py
avp/components/__init__.py
avp/components/__template__.ui
avp/components/color.py
avp/components/color.ui
avp/components/image.py
avp/components/image.ui
avp/components/life.py
avp/components/life.ui
avp/components/original.py
avp/components/original.ui
avp/components/sound.py
avp/components/sound.ui
avp/components/spectrum.py
avp/components/spectrum.ui
avp/components/text.py
avp/components/text.ui
avp/components/video.py
avp/components/video.ui
avp/components/waveform.py
avp/components/waveform.ui
avp/core.py
avp/encoder-options.json
avp/gui/__init__.py
avp/gui/actions.py
avp/gui/background.png
avp/gui/mainwindow.py
avp/gui/mainwindow.ui
avp/gui/presetmanager.py
avp/gui/presetmanager.ui
avp/gui/preview_thread.py
avp/gui/preview_win.py
avp/gui/undostack.py
avp/toolkit/__init__.py
avp/toolkit/common.py
avp/toolkit/ffmpeg.py
avp/toolkit/frame.py
avp/toolkit/visualizer.py
avp/video_thread.py
audio_visualizer_python-2.2.3.dist-info/WHEEL
audio_visualizer_python-2.2.3.dist-info/entry_points.txt
audio_visualizer_python-2.2.3.dist-info/METADATA
audio_visualizer_python-2.2.3.dist-info/RECORD
