Metadata-Version: 2.4
Name: audio-visualizer-python
Version: 2.2.3
Summary: Create audio visualization videos from a GUI or commandline
Keywords: visualizer,visualization,fft,ffmpeg,podcast
Author: Martin Kaistra, Brianna Rainey, DH4, HunterwolfAT, rikai
Author-email: Martin Kaistra <admin@djfun.de>, Brianna Rainey <brianna@tassaron.com>, DH4 <wayne@bitstorm.pw>, HunterwolfAT <hunterwolf0815@gmail.com>
License-Expression: MIT
Classifier: Development Status :: 5 - Production/Stable
Classifier: License :: OSI Approved :: MIT License
Classifier: Programming Language :: Python :: 3 :: Only
Classifier: Intended Audience :: End Users/Desktop
Classifier: Topic :: Multimedia :: Video
Requires-Dist: numpy>=2.4.1
Requires-Dist: pillow>=12.1.0
Requires-Dist: pyqt6>=6.10.2
Maintainer: Brianna Rainey
Maintainer-email: Brianna Rainey <brianna@tassaron.com>
Requires-Python: >=3.12
Project-URL: repository, https://github.com/djfun/audio-visualizer-python
